pystdatm/__init__.py
pystdatm/constants.py
pystdatm/mesosphere.py
pystdatm/stratopause.py
pystdatm/stratosphere.py
pystdatm/tropopause.py
pystdatm/troposphere.py
pystdatm-0.2.1.dist-info/licenses/LICENSE
pystdatm-0.2.1.dist-info/METADATA
pystdatm-0.2.1.dist-info/WHEEL
pystdatm-0.2.1.dist-info/top_level.txt
pystdatm-0.2.1.dist-info/RECORD
