Metadata-Version: 2.4
Name: pystdatm
Version: 0.2.1
Summary: Python Package for Standard Atmosphere
Author-email: Xero64 <xero64@gmail.com>
License-Expression: MIT
Project-URL: Homepage, https://github.com/Xero64/pystdatm
Project-URL: Issues, https://github.com/Xero64/pystdatm/issues
Classifier: Programming Language :: Python :: 3
Classifier: Operating System :: OS Independent
Requires-Python: >=3.10
License-File: LICENSE
Requires-Dist: numpy
Dynamic: license-file
